omnibus/.revision
omnibus/__about__.py
omnibus/__init__.py
omnibus/c3.py
omnibus/caches.py
omnibus/callables.py
omnibus/check.py
omnibus/code.py
omnibus/collections.py
omnibus/defs.py
omnibus/docker.py
omnibus/dynamic.py
omnibus/inject.py
omnibus/iterables.py
omnibus/lang.py
omnibus/libc.py
omnibus/logs.py
omnibus/os.py
omnibus/properties.py
omnibus/pydevd.py
omnibus/reflect.py
omnibus/replserver.py
omnibus/revision.py
omnibus/slotsdict.py
omnibus/toolz.py
omnibus-0.0.36.dist-info/METADATA
omnibus-0.0.36.dist-info/WHEEL
omnibus-0.0.36.dist-info/top_level.txt
omnibus-0.0.36.dist-info/RECORD
