Metadata-Version: 2.1
Name: omnibus
Version: 0.0.36
Summary: UNKNOWN
Home-page: https://github.com/wrmsr/omnibus
Author: wrmsr
License: UNKNOWN
Platform: UNKNOWN
Classifier: Intended Audience :: Developers
Classifier: Programming Language :: Python :: 3
Classifier: Programming Language :: Python :: 3.8
Classifier: Programming Language :: Python :: Implementation :: CPython
Classifier: Programming Language :: Python
Requires-Python: >=3.7
Requires-Dist: toolz (>=0.9.0)
Provides-Extra: bintrees
Requires-Dist: bintrees (>=0.2.7) ; extra == 'bintrees'
Provides-Extra: cytoolz
Requires-Dist: cytoolz (>=0.9.0) ; extra == 'cytoolz'
Provides-Extra: docker
Requires-Dist: docker (>=3.7.0) ; extra == 'docker'
Provides-Extra: sortedcontainers
Requires-Dist: sortedcontainers (>=2.1.0) ; extra == 'sortedcontainers'
